setup.py
CommonPart/__init__.py
CommonPart.egg-info/PKG-INFO
CommonPart.egg-info/SOURCES.txt
CommonPart.egg-info/dependency_links.txt
CommonPart.egg-info/requires.txt
CommonPart.egg-info/top_level.txt
CommonPart/build/__init__.py
CommonPart/build/lib/__init__.py
CommonPart/build/lib/combuiltin/__init__.py
CommonPart/build/lib/combuiltin/combuiltin.py
CommonPart/build/lib/combuiltin/sexception.py
CommonPart/build/lib/commonvar/__init__.py
CommonPart/build/lib/commonvar/commonvar.py
CommonPart/build/lib/smysql/__init__.py
CommonPart/build/lib/smysql/config.py
CommonPart/build/lib/smysql/mysql_mul/__init__.py
CommonPart/build/lib/smysql/mysql_single/__init__.py
CommonPart/build/lib/smysql/mysql_single/single_mysqldb.py
CommonPart/build/lib/sredis/__init__.py
CommonPart/build/lib/sredis/opredis.py
CommonPart/combuiltin/__init__.py
CommonPart/combuiltin/combuiltin.py
CommonPart/combuiltin/sexception.py
CommonPart/commonvar/__init__.py
CommonPart/commonvar/commonvar.py
CommonPart/smysql/__init__.py
CommonPart/smysql/config.py
CommonPart/smysql/mysql_mul/__init__.py
CommonPart/smysql/mysql_single/__init__.py
CommonPart/smysql/mysql_single/single_mysqldb.py
CommonPart/sredis/__init__.py
CommonPart/sredis/opredis.py